{
"type": "FeatureCollection",
"name": "eu_bbox_points",
"crs": { "type": "name", "properties": { "name": "urn:ogc:def:crs:OGC:1.3:CRS84" } },
"features": [
{ "type": "Feature", "properties": { }, "geometry": { "type": "Point", "coordinates": [ -2.630270672574249, 35.240117 ] } },
{ "type": "Feature", "properties": { }, "geometry": { "type": "Point", "coordinates": [ 7.493295182277255, 35.240117 ] } },
{ "type": "Feature", "properties": { }, "geometry": { "type": "Point", "coordinates": [ 17.616861037128757, 35.240117 ] } },
{ "type": "Feature", "properties": { }, "geometry": { "type": "Point", "coordinates": [ 27.74042689198026, 35.240117 ] } },
{ "type": "Feature", "properties": { }, "geometry": { "type": "Point", "coordinates": [ 37.863992746831762, 35.240117 ] } },
{ "type": "Feature", "properties": { }, "geometry": { "type": "Point", "coordinates": [ 47.987558601683276, 35.240117 ] } },
{ "type": "Feature", "properties": { }, "geometry": { "type": "Point", "coordinates": [ 55.9578555, 36.97958050996963 ] } },
{ "type": "Feature", "properties": { }, "geometry": { "type": "Point", "coordinates": [ 55.9578555, 44.628412758138722 ] } },
{ "type": "Feature", "properties": { }, "geometry": { "type": "Point", "coordinates": [ 55.9578555, 51.387696183982825 ] } },
{ "type": "Feature", "properties": { }, "geometry": { "type": "Point", "coordinates": [ 55.9578555, 57.27779861756057 ] } },
{ "type": "Feature", "properties": { }, "geometry": { "type": "Point", "coordinates": [ 50.896072572574248, 59.913868799999982 ] } },
{ "type": "Feature", "properties": { }, "geometry": { "type": "Point", "coordinates": [ 40.772506717722742, 59.913868799999982 ] } },
{ "type": "Feature", "properties": { }, "geometry": { "type": "Point", "coordinates": [ 30.648940862871228, 59.913868799999982 ] } },
{ "type": "Feature", "properties": { }, "geometry": { "type": "Point", "coordinates": [ 20.525375008019722, 59.913868799999982 ] } },
{ "type": "Feature", "properties": { }, "geometry": { "type": "Point", "coordinates": [ 10.401809153168243, 59.913868799999982 ] } },
{ "type": "Feature", "properties": { }, "geometry": { "type": "Point", "coordinates": [ 0.27824329831671, 59.913868799999982 ] } },
{ "type": "Feature", "properties": { }, "geometry": { "type": "Point", "coordinates": [ -7.6920536, 58.816756211007778 ] } },
{ "type": "Feature", "properties": { }, "geometry": { "type": "Point", "coordinates": [ -7.6920536, 53.166931616695294 ] } },
{ "type": "Feature", "properties": { }, "geometry": { "type": "Point", "coordinates": [ -7.6920536, 46.661433539514455 ] } },
{ "type": "Feature", "properties": { }, "geometry": { "type": "Point", "coordinates": [ -7.6920536, 39.267318079267703 ] } }
]
}
